AUTHORS.rst
CONTRIBUTING.rst
HISTORY.rst
LICENSE
MANIFEST.in
README.rst
setup.cfg
setup.py
docs/Makefile
docs/authors.rst
docs/conf.py
docs/contributing.rst
docs/history.rst
docs/index.rst
docs/installation.rst
docs/make.bat
docs/readme.rst
docs/usage.rst
docs/_build/html/_static/ajax-loader.gif
docs/_build/html/_static/comment-bright.png
docs/_build/html/_static/comment-close.png
docs/_build/html/_static/comment.png
docs/_build/html/_static/down-pressed.png
docs/_build/html/_static/down.png
docs/_build/html/_static/file.png
docs/_build/html/_static/minus.png
docs/_build/html/_static/plus.png
docs/_build/html/_static/up-pressed.png
docs/_build/html/_static/up.png
mbin/__init__.py
mbin/baxh5_read.py
mbin/bhtsne.py
mbin/cmph5_read.py
mbin/controls.py
mbin/mbin.py
mbin/motif_tools.py
mbin/motifs.py
mbin/multiproc.py
mbin/profiles.py
mbin/read_scanner.py
mbin/visualize.py
mbin.egg-info/PKG-INFO
mbin.egg-info/SOURCES.txt
mbin.egg-info/dependency_links.txt
mbin.egg-info/entry_points.txt
mbin.egg-info/not-zip-safe
mbin.egg-info/requires.txt
mbin.egg-info/top_level.txt