Metadata-Version: 1.1
Name: mbin
Version: 1.1.1
Summary: mBin: a methylation-based binning framework for metagenomic SMRT sequencing reads
Home-page: https://github.com/fanglab/mbin
Author: John Beaulaurier
Author-email: john.beaulaurier@gmail.com
License: CC BY-NC-SA 4.0 license
Keywords: mbin methylation sequencing binning metagenomic
Platform: UNKNOWN
Classifier: Development Status :: 5 - Production/Stable
Classifier: Intended Audience :: Developers
Classifier: License :: Free for non-commercial use
Classifier: Natural Language :: English
Classifier: Programming Language :: Python :: 2
Classifier: Programming Language :: Python :: 2.7
